pypyrus_logbook/__init__.py
pypyrus_logbook/conf.py
pypyrus_logbook/formatter.py
pypyrus_logbook/header.py
pypyrus_logbook/logger.py
pypyrus_logbook/output.py
pypyrus_logbook/record.py
pypyrus_logbook/sysinfo.py
pypyrus_logbook/utils.py
pypyrus_logbook-0.3.0.dist-info/LICENSE
pypyrus_logbook-0.3.0.dist-info/METADATA
pypyrus_logbook-0.3.0.dist-info/WHEEL
pypyrus_logbook-0.3.0.dist-info/top_level.txt
pypyrus_logbook-0.3.0.dist-info/RECORD
