Metadata-Version: 2.1
Name: pypyrus-logbook
Version: 0.3.0
Summary: Module for extended logging in Python.
Home-page: https://github.com/t3eHawk/logbook
Author: Timur Faradzhov
Author-email: timurfaradzhov@gmail.com
License: MIT
Platform: UNKNOWN
Classifier: Programming Language :: Python :: 3
Classifier: License :: OSI Approved :: MIT License
Classifier: Operating System :: OS Independent
Requires-Dist: sqlalchemy (>=1.3.1)
